safer_prompt_toolkit/__init__.py
safer_prompt_toolkit/_extra_prompt_toolkit_utilities.py
safer_prompt_toolkit/_safer_prompt_toolkit.py
safer_prompt_toolkit-1.8.dist-info/LICENSE
safer_prompt_toolkit-1.8.dist-info/METADATA
safer_prompt_toolkit-1.8.dist-info/WHEEL
safer_prompt_toolkit-1.8.dist-info/top_level.txt
safer_prompt_toolkit-1.8.dist-info/RECORD
