Metadata-Version: 2.1
Name: safer-prompt-toolkit
Version: 1.8
Summary: a wrapper to prompt-toolkit, designed to provide a fallback for some of prompt-toolkit's functionality when operating from a place where prompt-toolkit can't run
Home-page: https://github.com/LiorAvrahami/safer-prompt-toolkit
Author: Lior Avrahami
License: UNKNOWN
Platform: UNKNOWN
Classifier: Programming Language :: Python :: 3
Classifier: License :: OSI Approved :: MIT License
Classifier: Operating System :: OS Independent
Requires-Python: >=3.0
License-File: LICENSE
Requires-Dist: docutils
Requires-Dist: prompt-toolkit (>=3.0)
